automcp.py
automcp-0.1.0.dist-info/METADATA
automcp-0.1.0.dist-info/WHEEL
automcp-0.1.0.dist-info/top_level.txt
automcp-0.1.0.dist-info/RECORD
