Metadata-Version: 2.4
Name: automcp
Version: 0.1.0
Summary: Automatic MCP bindings for applications
Requires-Python: >=3.8
